Metadata-Version: 2.4
Name: PyP6XER
Version: 1.16.0
Summary: Python library for parsing and manipulating Primavera P6 XER files
Home-page: https://github.com/HassanEmam/PyP6Xer
Author: Hassan Emam
Author-email: Hassan Emam <hassan.emam@hotmail.com>
Maintainer-email: Hassan Emam <hassan.emam@hotmail.com>
License: LGPL-2.1
Project-URL: Homepage, https://github.com/HassanEmam/PyP6Xer
Project-URL: Documentation, https://hassanemam.github.io/PyP6Xer/
Project-URL: Repository, https://github.com/HassanEmam/PyP6Xer.git
Project-URL: Bug Tracker, https://github.com/HassanEmam/PyP6Xer/issues
Project-URL: Changelog, https://github.com/HassanEmam/PyP6Xer/blob/master/CHANGELOG.md
Keywords: primavera,p6,xer,project management,scheduling,construction,engineering,parser,dcma
Classifier: Development Status :: 4 - Beta
Classifier: Intended Audience :: End Users/Desktop
Classifier: Intended Audience :: Developers
Classifier: License :: OSI Approved :: GNU Lesser General Public License v2 (LGPLv2)
Classifier: Operating System :: OS Independent
Classifier: Programming Language :: Python :: 3
Classifier: Programming Language :: Python :: 3.8
Classifier: Programming Language :: Python :: 3.9
Classifier: Programming Language :: Python :: 3.10
Classifier: Programming Language :: Python :: 3.11
Classifier: Programming Language :: Python :: 3.12
Classifier: Topic :: Office/Business :: Scheduling
Classifier: Topic :: Scientific/Engineering
Classifier: Topic :: Software Development :: Libraries :: Python Modules
Requires-Python: >=3.8
License-File: LICENSE
Provides-Extra: dev
Requires-Dist: pytest>=6.0; extra == "dev"
Requires-Dist: pytest-cov>=2.0; extra == "dev"
Requires-Dist: black>=21.0; extra == "dev"
Requires-Dist: flake8>=3.8; extra == "dev"
Requires-Dist: mypy>=0.900; extra == "dev"
Provides-Extra: docs
Requires-Dist: sphinx>=5.0.0; extra == "docs"
Requires-Dist: sphinx-rtd-theme>=1.0.0; extra == "docs"
Requires-Dist: sphinx-autoapi>=2.0.0; extra == "docs"
Requires-Dist: myst-parser>=0.18.0; extra == "docs"
Requires-Dist: sphinx-copybutton>=0.5.0; extra == "docs"
Requires-Dist: sphinxext-opengraph>=0.6.0; extra == "docs"
Provides-Extra: test
Requires-Dist: pytest>=6.0; extra == "test"
Requires-Dist: pytest-cov>=2.0; extra == "test"
Dynamic: author
Dynamic: home-page
Dynamic: license-file
Dynamic: requires-python
